Workbook
Name Slicer_Region: #N/A

Sheet Sales_Data
A1: Order_ID | B1: Months | C1: Date | D1: Salesperson | E1: Region | F1: Product | G1: Category | H1: Units_Sold | I1: Unit_Price | J1: Discount_% | K1: Revenue | L1: Cost | M1: Profit
A2: ORD-001 | B2: =TEXT(Table1[[#This Row],[Date]],"mmm") -> Jan | C2: 2024-01-05 | D2: Ali Hassan | E2: North | F2: Laptop Pro | G2: Electronics | H2: 5 | I2: 1200 | J2: 0.05 | K2: =I2*H2*(1-J2) -> 5700 | L2: =H2*800 -> 4000 | M2: =K2-L2 -> 1700
A3: ORD-002 | B3: =TEXT(Table1[[#This Row],[Date]],"mmm") -> Jan | C3: 2024-01-12 | D3: Sara Ahmed | E3: South | F3: Office Chair | G3: Furniture | H3: 20 | I3: 350 | J3: 0.1 | K3: =I3*H3*(1-J3) -> 6300 | L3: =H3*200 -> 4000 | M3: =K3-L3 -> 2300
A4: ORD-003 | B4: =TEXT(Table1[[#This Row],[Date]],"mmm") -> Jan | C4: 2024-01-18 | D4: Bilal Khan | E4: East | F4: Printer X | G4: Electronics | H4: 8 | I4: 450 | J4: 0 | K4: =I4*H4*(1-J4) -> 3600 | L4: =H4*280 -> 2240 | M4: =K4-L4 -> 1360
A5: ORD-004 | B5: =TEXT(Table1[[#This Row],[Date]],"mmm") -> Jan | C5: 2024-01-25 | D5: Fatima Mir | E5: West | F5: Standing Desk | G5: Furniture | H5: 12 | I5: 600 | J5: 0.08 | K5: =I5*H5*(1-J5) -> 6624 | L5: =H5*350 -> 4200 | M5: =K5-L5 -> 2424
A6: ORD-005 | B6: =TEXT(Table1[[#This Row],[Date]],"mmm") -> Feb | C6: 2024-02-03 | D6: Ali Hassan | E6: North | F6: Laptop Pro | G6: Electronics | H6: 7 | I6: 1200 | J6: 0.05 | K6: =I6*H6*(1-J6) -> 7980 | L6: =H6*800 -> 5600 | M6: =K6-L6 -> 2380
A7: ORD-006 | B7: =TEXT(Table1[[#This Row],[Date]],"mmm") -> Feb | C7: 2024-02-10 | D7: Sara Ahmed | E7: South | F7: Headphones | G7: Electronics | H7: 30 | I7: 120 | J7: 0 | K7: =I7*H7*(1-J7) -> 3600 | L7: =H7*60 -> 1800 | M7: =K7-L7 -> 1800
A8: ORD-007 | B8: =TEXT(Table1[[#This Row],[Date]],"mmm") -> Feb | C8: 2024-02-14 | D8: Bilal Khan | E8: East | F8: Bookshelf | G8: Furniture | H8: 15 | I8: 200 | J8: 0.05 | K8: =I8*H8*(1-J8) -> 2850 | L8: =H8*110 -> 1650 | M8: =K8-L8 -> 1200
A9: ORD-008 | B9: =TEXT(Table1[[#This Row],[Date]],"mmm") -> Feb | C9: 2024-02-20 | D9: Fatima Mir | E9: West | F9: Monitor 27 | G9: Electronics | H9: 10 | I9: 320 | J9: 0.1 | K9: =I9*H9*(1-J9) -> 2880 | L9: =H9*190 -> 1900 | M9: =K9-L9 -> 980
A10: ORD-009 | B10: =TEXT(Table1[[#This Row],[Date]],"mmm") -> Mar | C10: 2024-03-02 | D10: Ali Hassan | E10: North | F10: Keyboard | G10: Electronics | H10: 50 | I10: 80 | J10: 0 | K10: =I10*H10*(1-J10) -> 4000 | L10: =H10*40 -> 2000 | M10: =K10-L10 -> 2000
A11: ORD-010 | B11: =TEXT(Table1[[#This Row],[Date]],"mmm") -> Mar | C11: 2024-03-09 | D11: Sara Ahmed | E11: South | F11: Laptop Pro | G11: Electronics | H11: 4 | I11: 1200 | J11: 0.05 | K11: =I11*H11*(1-J11) -> 4560 | L11: =H11*800 -> 3200 | M11: =K11-L11 -> 1360
A12: ORD-011 | B12: =TEXT(Table1[[#This Row],[Date]],"mmm") -> Mar | C12: 2024-03-15 | D12: Bilal Khan | E12: East | F12: Office Chair | G12: Furniture | H12: 25 | I12: 350 | J12: 0.1 | K12: =I12*H12*(1-J12) -> 7875 | L12: =H12*200 -> 5000 | M12: =K12-L12 -> 2875
A13: ORD-012 | B13: =TEXT(Table1[[#This Row],[Date]],"mmm") -> Mar | C13: 2024-03-22 | D13: Fatima Mir | E13: West | F13: Printer X | G13: Electronics | H13: 6 | I13: 450 | J13: 0 | K13: =I13*H13*(1-J13) -> 2700 | L13: =H13*280 -> 1680 | M13: =K13-L13 -> 1020
A14: ORD-013 | B14: =TEXT(Table1[[#This Row],[Date]],"mmm") -> Apr | C14: 2024-04-01 | D14: Ali Hassan | E14: North | F14: Monitor 27 | G14: Electronics | H14: 14 | I14: 320 | J14: 0.1 | K14: =I14*H14*(1-J14) -> 4032 | L14: =H14*190 -> 2660 | M14: =K14-L14 -> 1372
A15: ORD-014 | B15: =TEXT(Table1[[#This Row],[Date]],"mmm") -> Apr | C15: 2024-04-08 | D15: Sara Ahmed | E15: South | F15: Standing Desk | G15: Furniture | H15: 8 | I15: 600 | J15: 0.08 | K15: =I15*H15*(1-J15) -> 4416 | L15: =H15*350 -> 2800 | M15: =K15-L15 -> 1616
A16: ORD-015 | B16: =TEXT(Table1[[#This Row],[Date]],"mmm") -> Apr | C16: 2024-04-15 | D16: Bilal Khan | E16: East | F16: Headphones | G16: Electronics | H16: 40 | I16: 120 | J16: 0 | K16: =I16*H16*(1-J16) -> 4800 | L16: =H16*60 -> 2400 | M16: =K16-L16 -> 2400
A17: ORD-016 | B17: =TEXT(Table1[[#This Row],[Date]],"mmm") -> Apr | C17: 2024-04-22 | D17: Fatima Mir | E17: West | F17: Laptop Pro | G17: Electronics | H17: 3 | I17: 1200 | J17: 0.05 | K17: =I17*H17*(1-J17) -> 3420 | L17: =H17*800 -> 2400 | M17: =K17-L17 -> 1020
A18: ORD-017 | B18: =TEXT(Table1[[#This Row],[Date]],"mmm") -> May | C18: 2024-05-05 | D18: Ali Hassan | E18: North | F18: Bookshelf | G18: Furniture | H18: 18 | I18: 200 | J18: 0.05 | K18: =I18*H18*(1-J18) -> 3420 | L18: =H18*110 -> 1980 | M18: =K18-L18 -> 1440
A19: ORD-018 | B19: =TEXT(Table1[[#This Row],[Date]],"mmm") -> May | C19: 2024-05-12 | D19: Sara Ahmed | E19: South | F19: Keyboard | G19: Electronics | H19: 60 | I19: 80 | J19: 0 | K19: =I19*H19*(1-J19) -> 4800 | L19: =H19*40 -> 2400 | M19: =K19-L19 -> 2400
A20: ORD-019 | B20: =TEXT(Table1[[#This Row],[Date]],"mmm") -> May | C20: 2024-05-19 | D20: Bilal Khan | E20: East | F20: Monitor 27 | G20: Electronics | H20: 11 | I20: 320 | J20: 0.1 | K20: =I20*H20*(1-J20) -> 3168 | L20: =H20*190 -> 2090 | M20: =K20-L20 -> 1078
A21: ORD-020 | B21: =TEXT(Table1[[#This Row],[Date]],"mmm") -> May | C21: 2024-05-26 | D21: Fatima Mir | E21: West | F21: Office Chair | G21: Furniture | H21: 22 | I21: 350 | J21: 0.1 | K21: =I21*H21*(1-J21) -> 6930 | L21: =H21*200 -> 4400 | M21: =K21-L21 -> 2530

Sheet Vlookup & Xlookup
A1: Vlookup | D1: Xlookup
A2: Product | B2: Profit | D2: Product | E2: Profit
A3: office chair | B3: =VLOOKUP(A3,Table1[[Product]:[Profit]],8,FALSE) -> 2300 | D3: office chair | E3: =_xlfn.XLOOKUP(D3,Table1[Product],Table1[Profit]) -> 2300

Sheet sumif & countif
C2: Sumif | F2: Countif
C3: Region | D3: Revenue | F3: Region | G3: Order Count
C4: North | D4: =SUMIF(Table1[Region],'sumif & countif'!C4,Table1[Revenue]) -> 25132 | F4: west | G4: =COUNTIF(Table1[Region],'sumif & countif'!F4) -> 5

Sheet Dashboard
A1: 📊 SALES PERFORMANCE DASHBOARD 2024
A3: KEY METRICS
A4: Total Revenue ($) | B4: =SUM(Sales_Data!K2:K21) -> 93655 | C4: Total Orders | D4: =COUNTA(Sales_Data!A2:A21) -> 20
A5: Total Profit ($) | B5: =SUM(Sales_Data!M2:M21) -> 35255 | C5: Avg Order Revenue ($) | D5: =AVERAGE(Sales_Data!K2:K21) -> 4682.75
A6: Total Units Sold | B6: =SUM(Sales_Data!H2:H21) -> 368 | C6: Profit Margin (%) | D6: =SUM(Sales_Data!M2:M21)/SUM(Sales_Data!K2:K21) -> 0.37643479
A8: REVENUE BY REGION | E8: TOP SALESPERSON
A9: Region | B9: Revenue ($) | C9: Profit ($) | E9: Salesperson | F9: Revenue ($) | G9: Units
A10: North | B10: =SUMIF(Table1[Region],A10,Table1[Revenue]) -> 25132 | C10: =SUMIF(Table1[Region],Dashboard!A10,Table1[Profit]) -> 8892 | E10: Ali Hassan | F10: =SUMIF(Table1[Salesperson],E10,Table1[Revenue]) -> 25132 | G10: =SUMIF(Table1[Salesperson],E10,Table1[Units_Sold]) -> 94
A11: South | B11: =SUMIF(Table1[Region],A11,Table1[Revenue]) -> 23676 | C11: =SUMIF(Table1[Region],Dashboard!A11,Table1[Profit]) -> 9476 | E11: Sara Ahmed | F11: =SUMIF(Table1[Salesperson],E11,Table1[Revenue]) -> 23676 | G11: =SUMIF(Table1[Salesperson],E11,Table1[Units_Sold]) -> 122
A12: East | B12: =SUMIF(Table1[Region],A12,Table1[Revenue]) -> 22293 | C12: =SUMIF(Table1[Region],Dashboard!A12,Table1[Profit]) -> 8913 | E12: Bilal Khan | F12: =SUMIF(Table1[Salesperson],E12,Table1[Revenue]) -> 22293 | G12: =SUMIF(Table1[Salesperson],E12,Table1[Units_Sold]) -> 99
A13: West | B13: =SUMIF(Table1[Region],A13,Table1[Revenue]) -> 22554 | C13: =SUMIF(Table1[Region],Dashboard!A13,Table1[Profit]) -> 7974 | E13: Fatima Mir | F13: =SUMIF(Table1[Salesperson],E13,Table1[Revenue]) -> 22554 | G13: =SUMIF(Table1[Salesperson],E13,Table1[Units_Sold]) -> 53

Sheet Pivot table & charts
A1: Months | B1: Category | C1: Sum of Revenue
A2: Jan | B2: Electronics | C2: 9300 | F2: Region | G2: Sum of Revenue
B3: Furniture | C3: 12924 | F3: East | G3: 22293
A4: Jan Total | C4: 22224 | F4: North | G4: 25132
A5: Feb | B5: Electronics | C5: 14460 | F5: South | G5: 23676
B6: Furniture | C6: 2850 | F6: West | G6: 22554
A7: Feb Total | C7: 17310 | F7: Grand Total | G7: 93655
A8: Mar | B8: Electronics | C8: 11260
B9: Furniture | C9: 7875
A10: Mar Total | C10: 19135
A11: Apr | B11: Electronics | C11: 12252
B12: Furniture | C12: 4416
A13: Apr Total | C13: 16668
A14: May | B14: Electronics | C14: 7968
B15: Furniture | C15: 10350
A16: May Total | C16: 18318
A17: Grand Total | C17: 93655

Sheet 📋 Instructions
A1: PROJECT 1: SALES DASHBOARD
A3: SKILLS YOU WILL PRACTICE:
A4: 1. VLOOKUP / XLOOKUP – Look up product info across sheets
A5: 2. SUMIF / COUNTIF – Aggregate sales by region & salesperson
A6: 3. Pivot Tables – Drag-and-drop summary by category/month
A7: 4. Charts – Bar chart for region revenue, Line chart for monthly trend
A8: 5. Conditional Formatting – Highlight top/bottom performers
A10: STEP-BY-STEP TASKS:
A11: Step 1: Open Sales_Data sheet. Notice columns: Revenue = Units × Price × (1-Discount)
A12: Step 2: Go to Dashboard sheet. All KPIs use SUMIF/AVERAGE formulas — study them.
A13: Step 3: Select Sales_Data A1:L21 → Insert → Pivot Table → New Sheet
A14: Step 4: In Pivot Table: Rows=Month, Columns=Category, Values=Revenue (Sum)
... A22: Q: How do you handle missing data in Excel?
